deplicate_cli.py
deplicate_cli-0.1.1.dist-info/DESCRIPTION.rst
deplicate_cli-0.1.1.dist-info/METADATA
deplicate_cli-0.1.1.dist-info/RECORD
deplicate_cli-0.1.1.dist-info/WHEEL
deplicate_cli-0.1.1.dist-info/entry_points.txt
deplicate_cli-0.1.1.dist-info/metadata.json
deplicate_cli-0.1.1.dist-info/top_level.txt
deplicate_cli-0.1.1.dist-info/zip-safe
